MANIFEST.in
README.txt
bootstrap.py
buildout.cfg
setup.py
docs/HISTORY.txt
src/silva/__init__.py
src/silva.resourceinclude.egg-info/PKG-INFO
src/silva.resourceinclude.egg-info/SOURCES.txt
src/silva.resourceinclude.egg-info/dependency_links.txt
src/silva.resourceinclude.egg-info/namespace_packages.txt
src/silva.resourceinclude.egg-info/not-zip-safe
src/silva.resourceinclude.egg-info/requires.txt
src/silva.resourceinclude.egg-info/top_level.txt
src/silva/resourceinclude/__init__.py
src/silva/resourceinclude/collector.py
src/silva/resourceinclude/configure.zcml
src/silva/resourceinclude/interfaces.py
src/silva/resourceinclude/manager.py
src/silva/resourceinclude/merging.py
src/silva/resourceinclude/meta.zcml
src/silva/resourceinclude/monkeys.py
src/silva/resourceinclude/provider.py
src/silva/resourceinclude/resource.py
src/silva/resourceinclude/utils.py
src/silva/resourceinclude/zcml.py
src/silva/resourceinclude/martiansupport/__init__.py
src/silva/resourceinclude/martiansupport/resource.py
src/silva/resourceinclude/templates/provider.pt
src/silva/resourceinclude/tests/__init__.py
src/silva/resourceinclude/tests/test_resources.py
src/silva/resourceinclude/tests/collector/__init__.py
src/silva/resourceinclude/tests/collector/collector.txt
src/silva/resourceinclude/tests/collector/collector_fixtures/__init__.py
src/silva/resourceinclude/tests/collector/collector_fixtures/collector.py
src/silva/resourceinclude/tests/collector/collector_fixtures/static/file1.js
src/silva/resourceinclude/tests/collector/collector_fixtures/static/file2.js
src/silva/resourceinclude/tests/collector/collector_fixtures/static/style.css
src/silva/resourceinclude/tests/collector/collector_fixtures/static/images/img01.gif
src/silva/resourceinclude/tests/directive/__init__.py
src/silva/resourceinclude/tests/directive/oninterface.py
src/silva/resourceinclude/tests/merging/__init__.py
src/silva/resourceinclude/tests/merging/simple.py
src/silva/resourceinclude/tests/resource/__init__.py
src/silva/resourceinclude/tests/resource/grok.txt
src/silva/resourceinclude/tests/resource/requests.txt
src/silva/resourceinclude/tests/resource/resource.txt
src/silva/resourceinclude/tests/resource/grok_fixture/__init__.py
src/silva/resourceinclude/tests/resource/grok_fixture/view.py
src/silva/resourceinclude/tests/resource/grok_fixture/static/style.css
