Metadata-Version: 1.1
Name: silva.resourceinclude
Version: 2.2.1
Summary: z3c.resourceinclude like support for Silva
Home-page: https://github.com/silvacms/silva.resourceinclude
Author: Sylvain Viollon
Author-email: info@infrae.com
License: ZPL
Keywords: zope2 resourceinclude z3c
Platform: UNKNOWN
Classifier: Environment :: Web Environment
Classifier: Intended Audience :: Developers
Classifier: License :: OSI Approved :: Zope Public License
Classifier: Programming Language :: Python
Classifier: Topic :: Software Development :: Libraries :: Python Modules
Classifier: Framework :: Zope2
